{
  "project_info": {
    "project_number": "150660701274",
    "project_id": "mel-proyect",
    "storage_bucket": "mel-proyect.appspot.com"
  },
  "client": [
    {
      "client_info": {
        "mobilesdk_app_id": "1:150660701274:android:078d076d4c6a7023d24c63",
        "android_client_info": {
          "package_name": "com.pucmm.mel"
        }
      },
      "oauth_client": [
        {
          "client_id": "150660701274-62ph4fk6jlp42k1hodk796n4jlj04vad.apps.googleusercontent.com",
          "client_type": 3
        }
      ],
      "api_key": [
        {
          "current_key": "AIzaSyA0rZZrBgztQx12uzPcgUCkr4HUw_DdRDM"
        }
      ],
      "services": {
        "appinvite_service": {
          "other_platform_oauth_client": [
            {
              "client_id": "150660701274-62ph4fk6jlp42k1hodk796n4jlj04vad.apps.googleusercontent.com",
              "client_type": 3
            }
          ]
        }
      }
    }
  ],
  "configuration_version": "1"
}